thelemic_date.py
thelemic_date-5.93.dist-info/METADATA
thelemic_date-5.93.dist-info/WHEEL
thelemic_date-5.93.dist-info/top_level.txt
thelemic_date-5.93.dist-info/RECORD
