Metadata-Version: 2.1
Name: thelemic-date
Version: 5.93
Summary: A class for Thelemic date and time calculations.
Home-page: https://github.com/LilithXara/ThelemicDate
Author: Lilith Vala Xara
Author-email: lvx@93.is
Project-URL: Homepage, https://Thelema.Chat
Requires-Dist: flatlib
Requires-Dist: geopy
Requires-Dist: pytz
Requires-Dist: timezonefinder
